mydata/Anonymyzation.py
mydata/Processing.py
mydata/add_target.py
MydataShield-0.0.5.dist-info/LICENSE
MydataShield-0.0.5.dist-info/METADATA
MydataShield-0.0.5.dist-info/WHEEL
MydataShield-0.0.5.dist-info/top_level.txt
MydataShield-0.0.5.dist-info/RECORD
