Metadata-Version: 2.1
Name: MydataShield
Version: 0.0.5
Summary: Module to pseudonymize/anonymize Mydata
Home-page: https://github.com/jw0245/MyData
Author: gw0245
Author-email: gw0245@inzent.com
License: MIT
Platform: UNKNOWN
Requires-Python: >=3.6
